dogwalker/__init__.py
dogwalker/walker.py
dogwalker_testing-0.1.dist-info/METADATA
dogwalker_testing-0.1.dist-info/WHEEL
dogwalker_testing-0.1.dist-info/top_level.txt
dogwalker_testing-0.1.dist-info/RECORD
